graphviz_superfence.py
graphviz_superfence-0.0.1.dist-info/COPYING
graphviz_superfence-0.0.1.dist-info/METADATA
graphviz_superfence-0.0.1.dist-info/WHEEL
graphviz_superfence-0.0.1.dist-info/top_level.txt
graphviz_superfence-0.0.1.dist-info/RECORD
