Metadata-Version: 2.1
Name: graphviz_superfence
Version: 0.0.1
Summary: A superfence pymarkdown extension to convert graphviz dot code to svg
Home-page: https://graphviz-superfence.gitlab.io
Author: Davy Cottet
License: GNU General Public License v3.0
Platform: Any
Classifier: Programming Language :: Python :: 3
Classifier: License :: OSI Approved :: GNU General Public License v3 (GPLv3)
License-File: COPYING
Requires-Dist: markdown
Requires-Dist: pymdown-extensions
